pytest_html_object_storage/__init__.py
pytest_html_object_storage/minio.py
pytest_html_object_storage/plugin.py
pytest_html_object_storage/swift.py
pytest_html_object_storage/__pycache__/__init__.cpython-312.pyc
pytest_html_object_storage-0.2.1.data/data/pytest_html_object_storage/__init__.cpython-312.pyc
pytest_html_object_storage-0.2.1.dist-info/METADATA
pytest_html_object_storage-0.2.1.dist-info/WHEEL
pytest_html_object_storage-0.2.1.dist-info/entry_points.txt
pytest_html_object_storage-0.2.1.dist-info/top_level.txt
pytest_html_object_storage-0.2.1.dist-info/RECORD
