Metadata-Version: 2.1
Name: pytest-html-object-storage
Version: 0.2.1
Summary: Pytest report plugin for send HTML report on object-storage
Home-page: https://github.com/treussart/pytest-html-object-storage
Author: mtreussart
Author-email: matthieu@treussart.com
License: BSD
Keywords: py.test pytest zulip report
Classifier: Development Status :: 5 - Production/Stable
Classifier: Framework :: Pytest
Classifier: Intended Audience :: Developers
Classifier: License :: OSI Approved :: BSD License
Classifier: Operating System :: OS Independent
Classifier: Natural Language :: English
Classifier: Topic :: Software Development :: Quality Assurance
Classifier: Topic :: Software Development :: Testing
Classifier: Topic :: Utilities
Classifier: Programming Language :: Python
Classifier: Programming Language :: Python :: 3
Classifier: Programming Language :: Python :: 3.7
Classifier: Programming Language :: Python :: 3.8
Classifier: Programming Language :: Python :: 3.9
Classifier: Programming Language :: Python :: 3.10
Classifier: Programming Language :: Python :: 3.11
Classifier: Programming Language :: Python :: 3 :: Only
Requires-Python: >=3.7
Requires-Dist: pytest-html
Requires-Dist: minio
Requires-Dist: python-keystoneclient
Requires-Dist: python-swiftclient
